fmp_quant/FMP_Connect.py
fmp_quant/FMP_TA.py
fmp_quant/FMP_TARGET_PRICE.py
fmp_quant/FMP_TP.py
fmp_quant/__init__.py
fmp_quant-0.1.5.dist-info/METADATA
fmp_quant-0.1.5.dist-info/WHEEL
fmp_quant-0.1.5.dist-info/top_level.txt
fmp_quant-0.1.5.dist-info/RECORD
